{
  "openapi": "3.0.1",
  "info": {
    "title": "EFTEST",
    "version": "1.0"
  },
  "paths": {
    "/api/Books/Insert Data To Books": {
      "post": {
        "tags": [
          "Books"
        ],
        "requestBody": {
          "content": {
            "application/json": {
              "schema": {
                "$ref": "#/components/schemas/Book"
              }
            },
            "text/json": {
              "schema": {
                "$ref": "#/components/schemas/Book"
              }
            },
            "application/*+json": {
              "schema": {
                "$ref": "#/components/schemas/Book"
              }
            }
          }
        },
        "responses": {
          "200": {
            "description": "OK"
          }
        }
      }
    },
    "/api/Curency/ALL CUREENCY": {
      "get": {
        "tags": [
          "Curency"
        ],
        "responses": {
          "200": {
            "description": "OK",
            "content": {
              "text/plain": {
                "schema": {
                  "type": "array",
                  "items": {
                    "$ref": "#/components/schemas/CurrencyType"
                  }
                }
              },
              "application/json": {
                "schema": {
                  "type": "array",
                  "items": {
                    "$ref": "#/components/schemas/CurrencyType"
                  }
                }
              },
              "text/json": {
                "schema": {
                  "type": "array",
                  "items": {
                    "$ref": "#/components/schemas/CurrencyType"
                  }
                }
              }
            }
          }
        }
      }
    },
    "/api/Curency/Get Data By ID": {
      "get": {
        "tags": [
          "Curency"
        ],
        "parameters": [
          {
            "name": "id",
            "in": "query",
            "schema": {
              "type": "integer",
              "format": "int32"
            }
          }
        ],
        "responses": {
          "200": {
            "description": "OK",
            "content": {
              "text/plain": {
                "schema": {
                  "$ref": "#/components/schemas/Language"
                }
              },
              "application/json": {
                "schema": {
                  "$ref": "#/components/schemas/Language"
                }
              },
              "text/json": {
                "schema": {
                  "$ref": "#/components/schemas/Language"
                }
              }
            }
          }
        }
      }
    },
    "/ALL DATA": {
      "get": {
        "tags": [
          "Join"
        ],
        "responses": {
          "200": {
            "description": "OK",
            "content": {
              "text/plain": {
                "schema": {
                  "type": "array",
                  "items": { }
                }
              },
              "application/json": {
                "schema": {
                  "type": "array",
                  "items": { }
                }
              },
              "text/json": {
                "schema": {
                  "type": "array",
                  "items": { }
                }
              }
            }
          }
        }
      }
    },
    "/api/Lang/ALL Languages": {
      "get": {
        "tags": [
          "Lang"
        ],
        "responses": {
          "200": {
            "description": "OK",
            "content": {
              "text/plain": {
                "schema": {
                  "type": "array",
                  "items": {
                    "$ref": "#/components/schemas/Language"
                  }
                }
              },
              "application/json": {
                "schema": {
                  "type": "array",
                  "items": {
                    "$ref": "#/components/schemas/Language"
                  }
                }
              },
              "text/json": {
                "schema": {
                  "type": "array",
                  "items": {
                    "$ref": "#/components/schemas/Language"
                  }
                }
              }
            }
          }
        }
      }
    },
    "/api/Lang/get by id": {
      "get": {
        "tags": [
          "Lang"
        ],
        "parameters": [
          {
            "name": "id",
            "in": "query",
            "schema": {
              "type": "integer",
              "format": "int32"
            }
          }
        ],
        "responses": {
          "200": {
            "description": "OK",
            "content": {
              "text/plain": {
                "schema": {
                  "$ref": "#/components/schemas/Language"
                }
              },
              "application/json": {
                "schema": {
                  "$ref": "#/components/schemas/Language"
                }
              },
              "text/json": {
                "schema": {
                  "$ref": "#/components/schemas/Language"
                }
              }
            }
          }
        }
      }
    },
    "/api/Lang/BY NAME": {
      "get": {
        "tags": [
          "Lang"
        ],
        "parameters": [
          {
            "name": "name",
            "in": "query",
            "schema": {
              "type": "string"
            }
          }
        ],
        "responses": {
          "200": {
            "description": "OK",
            "content": {
              "text/plain": {
                "schema": {
                  "$ref": "#/components/schemas/Language"
                }
              },
              "application/json": {
                "schema": {
                  "$ref": "#/components/schemas/Language"
                }
              },
              "text/json": {
                "schema": {
                  "$ref": "#/components/schemas/Language"
                }
              }
            }
          }
        }
      }
    },
    "/api/Lang/Get Data By  Using Multiple": {
      "get": {
        "tags": [
          "Lang"
        ],
        "parameters": [
          {
            "name": "Title",
            "in": "query",
            "schema": {
              "type": "string"
            }
          },
          {
            "name": "Des",
            "in": "query",
            "schema": {
              "type": "string"
            }
          }
        ],
        "responses": {
          "200": {
            "description": "OK",
            "content": {
              "text/plain": {
                "schema": {
                  "$ref": "#/components/schemas/Language"
                }
              },
              "application/json": {
                "schema": {
                  "$ref": "#/components/schemas/Language"
                }
              },
              "text/json": {
                "schema": {
                  "$ref": "#/components/schemas/Language"
                }
              }
            }
          }
        }
      }
    },
    "/api/Lang/ListOfIds": {
      "get": {
        "tags": [
          "Lang"
        ],
        "responses": {
          "200": {
            "description": "OK",
            "content": {
              "text/plain": {
                "schema": {
                  "type": "array",
                  "items": {
                    "$ref": "#/components/schemas/Language"
                  }
                }
              },
              "application/json": {
                "schema": {
                  "type": "array",
                  "items": {
                    "$ref": "#/components/schemas/Language"
                  }
                }
              },
              "text/json": {
                "schema": {
                  "type": "array",
                  "items": {
                    "$ref": "#/components/schemas/Language"
                  }
                }
              }
            }
          }
        }
      }
    }
  },
  "components": {
    "schemas": {
      "Book": {
        "type": "object",
        "properties": {
          "id": {
            "type": "integer",
            "format": "int32"
          },
          "title": {
            "type": "string",
            "nullable": true
          },
          "description": {
            "type": "string",
            "nullable": true
          },
          "noOfPages": {
            "type": "integer",
            "format": "int32"
          },
          "isActive": {
            "type": "boolean"
          },
          "createdOn": {
            "type": "string",
            "format": "date-time"
          },
          "languageId": {
            "type": "integer",
            "format": "int32"
          },
          "language": {
            "$ref": "#/components/schemas/Language"
          }
        },
        "additionalProperties": false
      },
      "CurrencyType": {
        "type": "object",
        "properties": {
          "id": {
            "type": "integer",
            "format": "int32"
          },
          "currency": {
            "type": "string",
            "nullable": true
          },
          "description": {
            "type": "string",
            "nullable": true
          },
          "books": {
            "type": "array",
            "items": {
              "$ref": "#/components/schemas/Book"
            },
            "nullable": true
          }
        },
        "additionalProperties": false
      },
      "Language": {
        "type": "object",
        "properties": {
          "id": {
            "type": "integer",
            "format": "int32"
          },
          "title": {
            "type": "string",
            "nullable": true
          },
          "description": {
            "type": "string",
            "nullable": true
          },
          "books": {
            "$ref": "#/components/schemas/Book"
          }
        },
        "additionalProperties": false
      }
    }
  }
}